amplify_pytorch/__init__.py
amplify_pytorch/amplify.py
amplify_pytorch-0.0.5.dist-info/METADATA
amplify_pytorch-0.0.5.dist-info/WHEEL
amplify_pytorch-0.0.5.dist-info/licenses/LICENSE
amplify_pytorch-0.0.5.dist-info/RECORD
