Metadata-Version: 2.4
Name: amplify-pytorch
Version: 0.0.5
Summary: Amplify
Project-URL: Homepage, https://pypi.org/project/amplify-pytorch/
Project-URL: Repository, https://github.com/lucidrains/amplify-pytorch
Author-email: Phil Wang <lucidrains@gmail.com>
License: MIT License
License-File: LICENSE
Keywords: artificial intelligence,behavioral cloning,deep learning,robotics
Classifier: Development Status :: 4 - Beta
Classifier: Intended Audience :: Developers
Classifier: License :: OSI Approved :: MIT License
Classifier: Programming Language :: Python :: 3.9
Classifier: Topic :: Scientific/Engineering :: Artificial Intelligence
Requires-Python: >=3.9
Requires-Dist: accelerate
Requires-Dist: einops>=0.8.0
Requires-Dist: torch>=2.4
Requires-Dist: vector-quantize-pytorch
Requires-Dist: vit-pytorch>=1.11.6
Requires-Dist: x-transformers>=2.7.2
Provides-Extra: examples
Provides-Extra: test
Requires-Dist: pytest; extra == 'test'
